README.md
setup.py
./cvms/__init__.py
./cvms/conv.py
./cvms/attention/CrissCrossAttention.py
./cvms/attention/GAMAttention.py
./cvms/attention/NAMAttention.py
./cvms/attention/S2Attention.py
./cvms/attention/SEAttention.py
./cvms/attention/SKAttention.py
./cvms/attention/SOCA.py
./cvms/attention/ShuffleAttention.py
./cvms/attention/SimAM.py
./cvms/attention/__init__.py
cvms.egg-info/PKG-INFO
cvms.egg-info/SOURCES.txt
cvms.egg-info/dependency_links.txt
cvms.egg-info/top_level.txt